[
	{
		"filename": "data\/export_descr_unit.txt",
		"checksum": 1324478349
	},
	{
		"filename": "data\/export_descr_unit.txt",
		"checksum": 1324478349
	},
	{
		"filename": "data\/export_descr_buildings.txt",
		"checksum": 1324478349
	},
	{
		"filename": "data\/export_descr_buildings_enums.txt",
		"checksum": 1324478349
	},
	{
		"filename": "data\/text\/export_buildings.txt",
		"checksum": 2924144999
	},
	{
		"filename": "data\/text\/export_buildings_mac_de.txt",
		"checksum": 2924144999
	},
	{
		"filename": "data\/text\/export_buildings_mac_es.txt",
		"checksum": 2924144999
	},
	{
		"filename": "data\/text\/export_buildings_mac_fr.txt",
		"checksum": 2924144999
	},
	{
		"filename": "data\/text\/export_buildings_mac_it.txt",
		"checksum": 2924144999
	},
	{
		"filename": "data\/text\/export_buildings_mac_ru.txt",
		"checksum": 2924144999
	},
	{
		"filename": "data\/text\/export_buildings_mac_zh_cn.txt",
		"checksum": 2924144999
	},
	{
		"filename": "data\/world\/maps\/campaign\/imperial_campaign\/descr_strat.txt",
		"checksum": 2617507261
	},


	{
		"filename": "data\/ui\/unit_info\/carthage\/carthaginian_archer_info.tga",
		"checksum": "Blacklisted"
	},
	{
		"filename": "data\/ui\/unit_info_classic\/carthage\/carthaginian_archer_info.tga",
		"checksum": "Blacklisted"
	},
	{
		"filename": "data\/ui\/units\/carthage\/#carthaginian_archer.tga",
		"checksum": "Blacklisted"
	},
	{
		"filename": "data\/ui\/units_classic\/carthage\/#carthaginian_archer.tga",
		"checksum": "Blacklisted"
	},



	{
		"filename": "data\/ui\/unit_info\/spain\/barb_archer_dacian.tga",
		"checksum": "Blacklisted"
	},
	{
		"filename": "data\/ui\/unit_info_classic\/spain\/barb_archer_dacian.tga",
		"checksum": "Blacklisted"
	},
	{
		"filename": "data\/ui\/units\/spain\/#barb_archer_dacian.tga",
		"checksum": "Blacklisted"
	},
	{
		"filename": "data\/ui\/units_classic\/spain\/#barb_archer_dacian.tga",
		"checksum": "Blacklisted"
	},


	{
		"filename": "data\/ui\/unit_info\/britons\/barb_archer_dacian.tga",
		"checksum": "Blacklisted"
	},
	{
		"filename": "data\/ui\/unit_info_classic\/britons\/barb_archer_dacian.tga",
		"checksum": "Blacklisted"
	},
	{
		"filename": "data\/ui\/units\/britons\/#barb_archer_dacian.tga",
		"checksum": "Blacklisted"
	},
	{
		"filename": "data\/ui\/units_classic\/britons\/#barb_archer_dacian.tga",
		"checksum": "Blacklisted"
	},


	{
		"filename": "data\/ui\/unit_info\/macedon\/greek_hoplite_elite_info.tga",
		"checksum": "Blacklisted"
	},
	{
		"filename": "data\/ui\/unit_info_classic\/macedon\/greek_hoplite_elite_info.tga",
		"checksum": "Blacklisted"
	},

	{
		"filename": "data\/ui\/units\/macedon\/#greek_hoplite_elite.tga",
		"checksum": "Blacklisted"
	},
	{
		"filename": "data\/ui\/units_classic\/macedon\/#greek_hoplite_elite.tga",
		"checksum": "Blacklisted"
	},


	{
		"filename": "data\/ui\/unit_info\/seleucid\/greek_hoplite_elite_info.tga",
		"checksum": "Blacklisted"
	},
	{
		"filename": "data\/ui\/unit_info_classic\/seleucid\/greek_hoplite_elite_info.tga",
		"checksum": "Blacklisted"
	},

	{
		"filename": "data\/ui\/units\/seleucid\/#greek_hoplite_elite.tga",
		"checksum": "Blacklisted"
	},
	{
		"filename": "data\/ui\/units_classic\/seleucid\/#greek_hoplite_elite.tga",
		"checksum": "Blacklisted"
	},


	{
		"filename": "data\/ui\/unit_info\/greek_cities\/greek_royal_pikemen.tga",
		"checksum": "Blacklisted"
	},
	{
		"filename": "data\/ui\/unit_info_classic\/greek_cities\/greek_royal_pikemen.tga",
		"checksum": "Blacklisted"
	},

	{
		"filename": "data\/ui\/units\/greek_cities\/#greek_royal_pikemen.tga",
		"checksum": "Blacklisted"
	},
	{
		"filename": "data\/ui\/units_classic\/greek_cities\/#greek_royal_pikemen.tga",
		"checksum": "Blacklisted"
	}
	
]